LICENSE
README.md
setup.py
Autils.egg-info/PKG-INFO
Autils.egg-info/SOURCES.txt
Autils.egg-info/dependency_links.txt
Autils.egg-info/requires.txt
Autils.egg-info/top_level.txt
Autils.egg-info/zip-safe
autils/__init__.py
autils/authentication.py
autils/date.py
autils/datetime.py
autils/dict.py
autils/digits.py
autils/excepts.py
autils/logger.py
autils/od.py
autils/ost.py
autils/sign.py
autils/singleton.py
autils/string.py
tests/__init__.py
tests/test_date.py
tests/test_datetime.py
tests/test_dict.py
tests/test_digits.py
tests/test_dt.py
tests/test_logger.py
tests/test_ost.py
tests/test_sign.py
tests/test_str.py
tests/test_two_step.py