Metadata-Version: 2.1
Name: Autils
Version: 0.4.5
Summary: A hepler tools for kevin kong
Home-page: https://github.com/block-cat/autils
Author: blackcat
Author-email: kfx2007@163.com
License: GNU
Keywords: Autils
Classifier: License :: OSI Approved :: GNU Affero General Public License v3
Classifier: Programming Language :: Python
Classifier: Operating System :: OS Independent
Classifier: Topic :: Scientific/Engineering :: Astronomy
Classifier: Topic :: Scientific/Engineering :: GIS
Classifier: Topic :: Scientific/Engineering :: Mathematics
Classifier: Intended Audience :: Science/Research
Classifier: Intended Audience :: Developers
Classifier: Intended Audience :: Information Technology
License-File: LICENSE
Requires-Dist: requests
Requires-Dist: pyotp
Requires-Dist: pytz
Requires-Dist: python-dateutil
